luxy/__init__.py
luxy/api.py
luxy-0.0.7.dist-info/LICENSE
luxy-0.0.7.dist-info/METADATA
luxy-0.0.7.dist-info/WHEEL
luxy-0.0.7.dist-info/top_level.txt
luxy-0.0.7.dist-info/RECORD
