Metadata-Version: 2.1
Name: luxy
Version: 0.0.7
Summary: A Python wrapper for Yale's Lux API, provided by Yale University.
Home-page: https://github.com/project-lux/pylux
Author: William J.B. Mattingly
Classifier: Development Status :: 3 - Alpha
Classifier: Intended Audience :: Developers
Classifier: License :: OSI Approved :: Apache Software License
Classifier: Programming Language :: Python :: 3
Classifier: Programming Language :: Python :: 3.6
Classifier: Programming Language :: Python :: 3.7
Classifier: Programming Language :: Python :: 3.8
Classifier: Programming Language :: Python :: 3.9
Requires-Python: >=3.5
License-File: LICENSE
Requires-Dist: requests>=2.25.0
